bids2table/__init__.py
bids2table/__main__.py
bids2table/_entities.py
bids2table/_indexing.py
bids2table/_logging.py
bids2table/_metadata.py
bids2table/_pathlib.py
bids2table/_version.py
bids2table-2.1.2.dist-info/licenses/LICENSE
bids2table-2.1.2.dist-info/METADATA
bids2table-2.1.2.dist-info/WHEEL
bids2table-2.1.2.dist-info/entry_points.txt
bids2table-2.1.2.dist-info/top_level.txt
bids2table-2.1.2.dist-info/RECORD
