Metadata-Version: 2.4
Name: bids2table
Version: 2.1.2
Summary: Index BIDS datasets fast, locally or in the cloud.
Author-email: Connor Lane <connor.lane858@gmail.com>
License: MIT License
Project-URL: Homepage, https://github.com/childmindresearch/bids2table
Project-URL: Issues, https://github.com/childmindresearch/bids2table/issues
Classifier: Development Status :: 3 - Alpha
Classifier: Intended Audience :: Developers
Classifier: Topic :: Scientific/Engineering
Classifier: Programming Language :: Python :: 3
Classifier: Programming Language :: Python :: 3.11
Classifier: Programming Language :: Python :: 3.12
Classifier: Programming Language :: Python :: 3.13
Classifier: License :: OSI Approved :: MIT License
Classifier: Operating System :: POSIX
Classifier: Operating System :: Unix
Classifier: Operating System :: MacOS
Classifier: Operating System :: Microsoft :: Windows
Requires-Python: >=3.11
License-File: LICENSE
Requires-Dist: bidsschematools>=1.0
Requires-Dist: pyarrow>=20.0.0
Requires-Dist: tqdm>=4.67.1
Provides-Extra: s3
Requires-Dist: cloudpathlib[s3]>=0.21.0; extra == "s3"
Dynamic: license-file
